Metadata-Version: 1.0
Name: bino-gaus-dist
Version: 0.2
Summary: Gaussian and Binomial distributions
Home-page: UNKNOWN
Author: Gujjar Mohan Manjunath
Author-email: manjunathgujjar.147@gmail.com
License: UNKNOWN
Platform: UNKNOWN
